odoo/addons/l10n_it_bill_of_entry/README.rst
odoo/addons/l10n_it_bill_of_entry/__init__.py
odoo/addons/l10n_it_bill_of_entry/__manifest__.py
odoo/addons/l10n_it_bill_of_entry/demo/bill_of_entry_demo.xml
odoo/addons/l10n_it_bill_of_entry/i18n/it.po
odoo/addons/l10n_it_bill_of_entry/i18n/l10n_it_bill_of_entry.pot
odoo/addons/l10n_it_bill_of_entry/models/__init__.py
odoo/addons/l10n_it_bill_of_entry/models/account_move.py
odoo/addons/l10n_it_bill_of_entry/models/company.py
odoo/addons/l10n_it_bill_of_entry/readme/CONFIGURE.md
odoo/addons/l10n_it_bill_of_entry/readme/CONTRIBUTORS.md
odoo/addons/l10n_it_bill_of_entry/readme/DESCRIPTION.md
odoo/addons/l10n_it_bill_of_entry/readme/USAGE.md
odoo/addons/l10n_it_bill_of_entry/static/description/icon.png
odoo/addons/l10n_it_bill_of_entry/static/description/index.html
odoo/addons/l10n_it_bill_of_entry/tests/__init__.py
odoo/addons/l10n_it_bill_of_entry/tests/test_bill_of_entry.py
odoo/addons/l10n_it_bill_of_entry/views/account_invoice_view.xml
odoo/addons/l10n_it_bill_of_entry/views/company_view.xml
odoo_addon_l10n_it_bill_of_entry-18.0.1.0.0.3.dist-info/METADATA
odoo_addon_l10n_it_bill_of_entry-18.0.1.0.0.3.dist-info/WHEEL
odoo_addon_l10n_it_bill_of_entry-18.0.1.0.0.3.dist-info/top_level.txt
odoo_addon_l10n_it_bill_of_entry-18.0.1.0.0.3.dist-info/RECORD
