Metadata-Version: 2.1
Name: odoo-addon-l10n_it_bill_of_entry
Version: 18.0.1.0.0.3
Requires-Python: >=3.10
Requires-Dist: odoo==18.0.*
Summary: ITA - Bolle doganali
Home-page: https://github.com/OCA/l10n-italy
License: AGPL-3
Author: Agile Business Group, CQ Creativi Quadrati, TAKOBI, Odoo Community Association (OCA)
Author-email: support@odoo-community.org
Classifier: Programming Language :: Python
Classifier: Framework :: Odoo
Classifier: Framework :: Odoo :: 18.0
Classifier: License :: OSI Approved :: GNU Affero General Public License v3
